{
  "lastUpdate": "2025-09-27 11:32:02",
  "data": [
    {
      "title": "italy poland volleyball",
      "trafficCount": "500+",
      "pubDate": "Sat, 27 Sep 2025 02:30:00 -0700",
      "picture": "https://encrypted-tbn1.gstatic.com/images?q=tbn:ANd9GcRiqeS0pUnHp5OdF5ZQ0slKSAf1RE-a66EnTwMStGVluhFEa55-hfWA7ofn1tI",
      "pictureSource": "Volleyball World",
      "relatedSearch": [
        {
          "title": "Day 14: Curtains up for the semifinals!",
          "snippet": "",
          "url": "https://en.volleyballworld.com/volleyball/competitions/men-world-championship/news/day-14-curtains-up-for-the-semifinals",
          "source": "Volleyball World"
        },
        {
          "title": "Poland storm into semi-finals of volleyball World Championships with win over Turkey",
          "snippet": "",
          "url": "https://tvpworld.com/89101352/poland-into-semi-finals-of-volleyball-world-championships",
          "source": "TVP World"
        },
        {
          "title": "‘I Need Gold Medals’: Wilfredo Leon Wants a World Championship With Poland",
          "snippet": "",
          "url": "https://thegame-onemega.com/sports/volleyball/wilfredo-leon-wants-a-world-championship/",
          "source": "thegame-onemega.com"
        }
      ],
      "link": "https://imtaqin.id/"
    },
    {
      "title": "pasay city",
      "trafficCount": "100+",
      "pubDate": "Sat, 27 Sep 2025 01:30:00 -0700",
      "picture": "https://encrypted-tbn2.gstatic.com/images?q=tbn:ANd9GcQZ6y23d7ISORLMrXEVTWfnk47-pqRQNWKEmcvLoIN5Ogt-FpblI7eU3v9dlDI",
      "pictureSource": "Philippine News Agency",
      "relatedSearch": [
        {
          "title": "DSWD sends P22-M aid to Bicol as ‘Opong’ leaves thousands displaced",
          "snippet": "",
          "url": "https://www.pna.gov.ph/articles/1259719",
          "source": "Philippine News Agency"
        },
        {
          "title": "DSWD Calls For Volunteers Anew To Help Prepare Family Food Packs",
          "snippet": "",
          "url": "https://pageone.ph/dswd-calls-for-volunteers-anew-to-help-prepare-family-food-packs/",
          "source": "pageone.ph"
        },
        {
          "title": "DSWD distributes food to stranded passengers",
          "snippet": "",
          "url": "https://www.manilatimes.net/2025/09/27/news/national/dswd-distributes-food-to-stranded-passengers/2191212",
          "source": "The Manila Times"
        }
      ],
      "link": "https://imtaqin.id/"
    },
    {
      "title": "полша италия волейбол",
      "trafficCount": "50000+",
      "pubDate": "Sat, 27 Sep 2025 01:20:00 -0700",
      "picture": "https://encrypted-tbn3.gstatic.com/images?q=tbn:ANd9GcQZs6TfYXBe8TrHMu1kb2J6hogeex870b1CUstq2Qd3zMVQ4-oQfmx_qS8GkMg",
      "pictureSource": "bTV",
      "relatedSearch": [
        {
          "title": "България на финал! bTV ще излъчи историческия сблъсък за златото на Световното първенство по волейбол за мъже – тази неделя от 13:30 часа",
          "snippet": "",
          "url": "https://www.btv.bg/za-btv/spetsialno/balgarija-na-final-btv-shte-izlachi-istoricheskija-sblasak-za-zlatoto-na-svetovnoto-parvenstvo-po-volejbol-za-mazhe-tazi-nedelja-ot-13-30-chasa.html",
          "source": "bTV"
        },
        {
          "title": "NOVA ще излъчи финала на Световното първенство по волейбол",
          "snippet": "",
          "url": "https://nova.bg/news/view/2025/09/27/512055/nova-%D1%89%D0%B5-%D0%B8%D0%B7%D0%BB%D1%8A%D1%87%D0%B8-%D1%84%D0%B8%D0%BD%D0%B0%D0%BB%D0%B0-%D0%BD%D0%B0-%D1%81%D0%B2%D0%B5%D1%82%D0%BE%D0%B2%D0%BD%D0%BE%D1%82%D0%BE-%D0%BF%D1%8A%D1%80%D0%B2%D0%B5%D0%BD%D1%81%D1%82%D0%B2%D0%BE-%D0%BF%D0%BE-%D0%B2%D0%BE%D0%BB%D0%B5%D0%B9%D0%B1%D0%BE%D0%BB/",
          "source": "Nova.bg"
        },
        {
          "title": "55 години по-късно България отново е на финал на световно по волейбол",
          "snippet": "",
          "url": "https://www.mediapool.bg/55-godini-po-kasno-bulgaria-otnovo-e-na-final-na-svetovno-po-voleibol-news375683.html",
          "source": "Mediapool.bg"
        }
      ],
      "link": "https://imtaqin.id/"
    },
    {
      "title": "спортал",
      "trafficCount": "500+",
      "pubDate": "Sat, 27 Sep 2025 01:20:00 -0700",
      "picture": "https://encrypted-tbn0.gstatic.com/images?q=tbn:ANd9GcR3zGz88R9p2sGYaqsB8WsGw0ygwuNg5qhkPJLihVIAnwgxY9krtAAhCn8XFcs",
      "pictureSource": "Sportal.bg",
      "relatedSearch": [
        {
          "title": "Кой ще е съперник на България на финала? Полуфинал №2 Полша 0:1 Италия! Следете мача ТУК!",
          "snippet": "",
          "url": "https://sportal.bg/news-2025092710292479477",
          "source": "Sportal.bg"
        },
        {
          "title": "Ясен е първият 1/2-финал на Световното по волейбол",
          "snippet": "",
          "url": "https://www.flagman.bg/article/361395",
          "source": "Флагман.Бг"
        },
        {
          "title": "Европейският първенец се класира за 1/4-финалите на Мондиала във Филипините",
          "snippet": "",
          "url": "https://www.focus-news.net/sport/2713314.html",
          "source": "ФОКУС"
        }
      ],
      "link": "https://imtaqin.id/"
    },
    {
      "title": "bulgaria czech republic",
      "trafficCount": "500+",
      "pubDate": "Sat, 27 Sep 2025 00:10:00 -0700",
      "picture": "https://encrypted-tbn1.gstatic.com/images?q=tbn:ANd9GcQAgv77XahOQoREiSTFH6xi9IjB3H4DdM1wLQJ5vq1I-_gNrD7H2uxeXRSP0fs",
      "pictureSource": "Volleyball World",
      "relatedSearch": [
        {
          "title": "Czechia’s fairy tale continues into the semifinals!",
          "snippet": "",
          "url": "https://en.volleyballworld.com/volleyball/competitions/men-world-championship/news/czechia-s-fairy-tale-continues-into-the-semifinals",
          "source": "Volleyball World"
        },
        {
          "title": "Patrik Indra brings Czechia’s World Championship fairy tale to life in Manila",
          "snippet": "",
          "url": "https://www.fivb.com/patrik-indra-brings-czechias-world-championship-fairy-tale-to-life-in-manila/",
          "source": "FIVB"
        },
        {
          "title": "Iran into 2025 FIVB World Championship QFs",
          "snippet": "",
          "url": "https://nournews.ir/en/News-Print/247258",
          "source": "نورنیوز"
        }
      ],
      "link": "https://imtaqin.id/"
    },
    {
      "title": "ян гълъбов",
      "trafficCount": "500+",
      "pubDate": "Sat, 27 Sep 2025 00:00:00 -0700",
      "picture": "https://encrypted-tbn2.gstatic.com/images?q=tbn:ANd9GcTqcTvGfCsIx6SrinXTnDZ0wS98QnZWxQ7SSXuHgsB9206FmjtbmkBigr9o6hQ",
      "pictureSource": "Blitz.bg",
      "relatedSearch": [
        {
          "title": "Чех с българска кръв излиза срещу България утре",
          "snippet": "",
          "url": "https://blitz.bg/sport/voleybol/chekh-s-blgarska-krv-izliza-sreshchu-blgariya-utre_574475.html",
          "source": "Blitz.bg"
        },
        {
          "title": "Български внук ще ни спира в полуфинала с Чехия",
          "snippet": "",
          "url": "https://darik.bg/balgarski-vnuk-ste-ni-spira-v-polufinala-s-chehia~502141.html",
          "source": "Дарик - Новини, анализи и коментари - Darik.bg"
        },
        {
          "title": "Чехия продължава към четвъртфиналите на Световното",
          "snippet": "",
          "url": "https://www.focus-news.net/sport/2716216.html",
          "source": "ФОКУС"
        }
      ],
      "link": "https://imtaqin.id/"
    },
    {
      "title": "иво аръков",
      "trafficCount": "200+",
      "pubDate": "Sat, 27 Sep 2025 00:00:00 -0700",
      "picture": "https://encrypted-tbn2.gstatic.com/images?q=tbn:ANd9GcRU-9Tg1jKagRZ80FMdAZNYTFMCQ15BIiRZaVS6lonJEO59y3pXTbOXYqLNc18",
      "pictureSource": "Plovdiv24",
      "relatedSearch": [
        {
          "title": "Иво Аръков и Габи за първи път показаха сина си пред Деси Плевнелиева (ВИДЕО)",
          "snippet": "",
          "url": "https://www.plovdiv24.bg/novini/interesno/Ivo-Arukov-i-Gabi-za-purvi-put-pokazaha-sina-si-pred-Desi-Plevnelieva-2721727",
          "source": "Plovdiv24"
        },
        {
          "title": "Иво Аръков и любимата му Габи проговориха за връзката си",
          "snippet": "",
          "url": "https://www.bgdnes.bg/shou/article/21378522",
          "source": "bgdnes.bg"
        },
        {
          "title": "Честито на талантливия актьор Иво Аръков",
          "snippet": "",
          "url": "https://www.marica.bg/balgariq/obshtestvo/chestito-na-talantliviq-aktyor-ivo-arakov",
          "source": "marica.bg"
        }
      ],
      "link": "https://imtaqin.id/"
    },
    {
      "title": "flashscore",
      "trafficCount": "200+",
      "pubDate": "Fri, 26 Sep 2025 23:50:00 -0700",
      "picture": "https://encrypted-tbn2.gstatic.com/images?q=tbn:ANd9GcRpKnH3H0Z13ZofaLwQRQ3djPexC4EzVgFHyVw2kXxWCLMM3nHb0M8ujl70-cM",
      "pictureSource": "Flashscore.com",
      "relatedSearch": [
        {
          "title": "EXCLUSIVE: Piatek on helping Al-Duhail challenge for the title and Milan memories",
          "snippet": "",
          "url": "https://www.flashscore.com/news/soccer-qsl-exclusive-piatek-on-helping-al-duhail-challenge-for-the-title-and-milan-memories/UPw07tFs/",
          "source": "Flashscore.com"
        },
        {
          "title": "Hot shot: Yuan goes toe-to-toe with Swiatek in Beijing, finishes with flair",
          "snippet": "",
          "url": "https://www.wtatennis.com/videos/4370408/hot-shot-yuan-goes-toe-to-toe-with-swiatek-in-beijing-finishes-with-flair",
          "source": "WTA Tennis"
        },
        {
          "title": "Iga Swiatek advances to the third round at the China Open",
          "snippet": "",
          "url": "https://www.msn.com/en-us/sports/tennis/iga-swiatek-advances-to-the-third-round-at-the-china-open/ar-AA1NpjQo",
          "source": "MSN"
        }
      ],
      "link": "https://imtaqin.id/"
    },
    {
      "title": "volleyball world cup",
      "trafficCount": "2000+",
      "pubDate": "Fri, 26 Sep 2025 23:30:00 -0700",
      "picture": "https://encrypted-tbn2.gstatic.com/images?q=tbn:ANd9GcTcnh5ePxAQC5-hfyefUmRXVgxrY0HVM9flH8guzCHn6JzdIXQ_t5TmMgbiRZM",
      "pictureSource": "Volleyball World",
      "relatedSearch": [
        {
          "title": "Aleks Nikolov by far the best scorer so far",
          "snippet": "",
          "url": "https://en.volleyballworld.com/volleyball/competitions/men-world-championship/news/aleks-nikolov-by-far-the-best-scorer-so-far",
          "source": "Volleyball World"
        },
        {
          "title": "Polish journalist: Aleksandar Nikolov – favorite for MVP, two Bulgarians in the \"dream team\" of the World Championship",
          "snippet": "",
          "url": "https://volleyweek.bg/en/article/3549-Polish-journalist-Aleksandar-Nikolov-%E2%80%93-favorite-for-MVP-two-Bulgarians-in-the-dream-team-of-the-World-Championship",
          "source": "Volley Week"
        },
        {
          "title": "World Cup, Lube on display. The Biancorossi deserve applause.",
          "snippet": "",
          "url": "https://sport.quotidiano.net/en/volley/mondiale-lube-in-vetrina-biancorossi-af810445",
          "source": "Quotidiano Sportivo"
        }
      ],
      "link": "https://imtaqin.id/"
    },
    {
      "title": "бнт",
      "trafficCount": "100+",
      "pubDate": "Fri, 26 Sep 2025 23:30:00 -0700",
      "picture": "https://encrypted-tbn0.gstatic.com/images?q=tbn:ANd9GcTV9CBCFdiFBWmF-L_w1kgIsScEtFh26FKwn0R6KE3QG1Kz9nvlswsKtOi1J5s",
      "pictureSource": "offnews.bg",
      "relatedSearch": [
        {
          "title": "Стачката в БНТ се отлага",
          "snippet": "",
          "url": "https://offnews.bg/medii/stachkata-v-bnt-se-otlaga-852042.html",
          "source": "offnews.bg"
        },
        {
          "title": "Служителите в БНТ засега се отказаха да стачкуват",
          "snippet": "",
          "url": "https://www.dnevnik.bg/bulgaria/2025/09/23/4832172_slujiteli_v_bnt_se_otkazaha_zasega_da_stachkuvat/",
          "source": "Dnevnik"
        },
        {
          "title": "Предупредителните стачни действия на служители в БНТ се отлагат",
          "snippet": "",
          "url": "https://bnr.bg/post/102215057/predupreditelnite-stachni-deistvia-na-slujiteli-v-bnt-se-otlagat",
          "source": "БНР"
        }
      ],
      "link": "https://imtaqin.id/"
    }
  ]
}