{
  "lastUpdate": "2026-01-08 01:59:11",
  "data": [
    {
      "title": "地下鉄烏丸線",
      "trafficCount": "500+",
      "pubDate": "Wed, 7 Jan 2026 17:40:00 -0800",
      "picture": "https://encrypted-tbn0.gstatic.com/images?q=tbn:ANd9GcSqeePPoCCRSF_WX9Sth-H7UVxfr4LImf50xj7HXp0h36TFIYGNQy1J8zV4oFU",
      "pictureSource": "Yahoo!ニュース",
      "relatedSearch": [
        {
          "title": "【速報】京都市の地下鉄烏丸線・鞍馬口駅で人が線路転落 全線で運転見合わせ（京都新聞）",
          "snippet": "",
          "url": "https://news.yahoo.co.jp/articles/2d7bd59017fd99753e522e4e42cbb07ad76c8dd0",
          "source": "Yahoo!ニュース"
        },
        {
          "title": "【速報】京都市の地下鉄烏丸線・鞍馬口駅で人身事故 全線で運転見合わせ",
          "snippet": "",
          "url": "https://article.auone.jp/detail/1/2/5/473_5_r_20260108_1767835428982510",
          "source": "au Webポータル"
        },
        {
          "title": "京都市営烏丸線で人身事故 一部運転見合わせ",
          "snippet": "",
          "url": "https://topics.smt.docomo.ne.jp/article/rescuenow/nation/rescuenow-00000017836907?fm=latestnews",
          "source": "ｄメニューニュース"
        }
      ],
      "link": "https://imtaqin.id/"
    },
    {
      "title": "box",
      "trafficCount": "2000+",
      "pubDate": "Wed, 7 Jan 2026 17:30:00 -0800",
      "picture": "https://encrypted-tbn3.gstatic.com/images?q=tbn:ANd9GcTJZciDis87cyO1DbH0S44FAFNmcWye6Nu3orGPnYsyL8OyjRy4mfifO38lAGY",
      "pictureSource": "The Hollywood Reporter",
      "relatedSearch": [
        {
          "title": "Sydney Sweeney Eyeing Return for ‘The Housemaid’ Sequel, Paul Feig to Direct",
          "snippet": "",
          "url": "https://www.hollywoodreporter.com/movies/movie-news/housemaid-sequel-secret-sydney-sweeney-1236465639/",
          "source": "The Hollywood Reporter"
        },
        {
          "title": "‘The Housemaid’ Sequel in the Works With Sydney Sweeney and Paul Feig Returning",
          "snippet": "",
          "url": "https://variety.com/2026/film/news/the-housemaid-sequel-sydney-sweeney-paul-feig-1236624121/",
          "source": "Variety"
        },
        {
          "title": "Amanda Seyfried Says She Wants to Return for a Cameo in Housemaid Sequels: 'I Guarantee' It'll Happen",
          "snippet": "",
          "url": "https://people.com/amanda-seyfried-wants-return-housemaid-sequel-cameo-11879163",
          "source": "People.com"
        }
      ],
      "link": "https://imtaqin.id/"
    },
    {
      "title": "ノンストップ",
      "trafficCount": "200+",
      "pubDate": "Wed, 7 Jan 2026 17:30:00 -0800",
      "picture": "https://encrypted-tbn1.gstatic.com/images?q=tbn:ANd9GcTL35ZiLBeT9zU_dVH7rrDpBoeA9QhHzsVTf9S_nqLMjxBjKCDCfsBBMaxC-Ww",
      "pictureSource": "TVer",
      "relatedSearch": [
        {
          "title": "設楽＆豪華レギュラー陣が大阪・京都旅／1日目",
          "snippet": "",
          "url": "https://tver.jp/episodes/epq0wk7gq8",
          "source": "TVer"
        },
        {
          "title": "深澤辰哉がユニバ満喫！“ミニオン”カチューシャで“ちょこん”と座る姿に「ニコニコでかわいい」「メロすぎる」「彼氏感強くて神」とファン悶絶（THE FIRST TIMES）",
          "snippet": "",
          "url": "https://news.yahoo.co.jp/articles/dda01a9abb584de31edc2bbb0e43d23c4a7ad9eb",
          "source": "Yahoo!ニュース"
        },
        {
          "title": "深澤辰哉がユニバ満喫！“ミニオン”カチューシャで“ちょこん”と座る姿に「ニコニコでかわいい」「メロすぎる」「彼氏感強くて神」とファン悶絶 (2026年1月5日掲載)",
          "snippet": "",
          "url": "https://news.livedoor.com/topics/detail/30317925/",
          "source": "ライブドアニュース"
        }
      ],
      "link": "https://imtaqin.id/"
    },
    {
      "title": "ラプンツェル 実写",
      "trafficCount": "100+",
      "pubDate": "Wed, 7 Jan 2026 17:30:00 -0800",
      "picture": "https://encrypted-tbn0.gstatic.com/images?q=tbn:ANd9GcT6F_vwOYT6XIXl6_SOy1w8CPEZEBQGatNF3f3CfRxO33buO1Mh2CGlp7QgH4I",
      "pictureSource": "Yahoo!ニュース",
      "relatedSearch": [
        {
          "title": "実写版『塔の上のラプンツェル』キャストが決定！（シネマトゥデイ）",
          "snippet": "",
          "url": "https://news.yahoo.co.jp/articles/14937b95bc92d1d743937f80dd3f0a67ffaf4ce3",
          "source": "Yahoo!ニュース"
        },
        {
          "title": "ディズニー、実写版『タイタンズ・アンド・ゾンビーズ』のメインキャストを発表",
          "snippet": "",
          "url": "https://www.mixvale.com.br/2026/01/07/%E3%83%87%E3%82%A3%E3%82%BA%E3%83%8B%E3%83%BC%E3%80%81%E5%AE%9F%E5%86%99%E7%89%88%E3%80%8E%E3%82%BF%E3%82%A4%E3%82%BF%E3%83%B3%E3%82%BA%E3%83%BB%E3%82%A2%E3%83%B3%E3%83%89%E3%83%BB%E3%82%BE%E3%83%B3-j/amp/",
          "source": "Mix Vale"
        },
        {
          "title": "実写版『塔の上のラプンツェル』キャスト正式決定！ラプンツェル＆フリン役は誰？―― 大注目の若手スターを紹介",
          "snippet": "",
          "url": "https://hollywoodreporter.jp/movies/168365/",
          "source": "ハリウッド・リポーター・ジャパン"
        }
      ],
      "link": "https://imtaqin.id/"
    },
    {
      "title": "スポーツブル",
      "trafficCount": "500+",
      "pubDate": "Wed, 7 Jan 2026 17:20:00 -0800",
      "picture": "",
      "pictureSource": "",
      "relatedSearch": [],
      "link": "https://imtaqin.id/"
    },
    {
      "title": "milo manheim",
      "trafficCount": "200+",
      "pubDate": "Wed, 7 Jan 2026 17:20:00 -0800",
      "picture": "https://encrypted-tbn2.gstatic.com/images?q=tbn:ANd9GcQr7B03W8IA5_PJwM9IhO2dzvtuJUorJZ4VDjbNKeLiTt6VeGcGSC7MvrWhjuI",
      "pictureSource": "The Hollywood Reporter",
      "relatedSearch": [
        {
          "title": "‘Tangled’ Live-Action Movie Finds Its Leads: Teagan Croft, Milo Manheim (Exclusive)",
          "snippet": "",
          "url": "https://www.hollywoodreporter.com/movies/movie-news/tangled-live-action-movie-teagan-croft-milo-manheim-1236466753/",
          "source": "The Hollywood Reporter"
        },
        {
          "title": "Disney announces cast for live-action ‘Tangled’",
          "snippet": "",
          "url": "https://www.yahoo.com/entertainment/movies/articles/disney-announces-cast-live-action-012146089.html",
          "source": "Yahoo"
        },
        {
          "title": "Live-action ‘Tangled’ will star Teagan Croft and Milo Manheim as Rapunzel and Flynn Rider",
          "snippet": "",
          "url": "https://apnews.com/article/tangled-liveaction-teagan-croft-milo-manheim-825fe3a9656135dd55a74ad4c52277fa",
          "source": "AP News"
        }
      ],
      "link": "https://imtaqin.id/"
    },
    {
      "title": "東京エレクトロン 株価",
      "trafficCount": "200+",
      "pubDate": "Wed, 7 Jan 2026 17:20:00 -0800",
      "picture": "https://encrypted-tbn2.gstatic.com/images?q=tbn:ANd9GcT8bTXBNbV37Y6cuuF4nhGMhHUPO8TjNCp8exFQFyrDDFXmUPSIidBFmSBAvrc",
      "pictureSource": "かぶたん",
      "relatedSearch": [
        {
          "title": "【材料】 前日に動いた銘柄 part1レーザーテック、東京エレクトロン、フジクラなど",
          "snippet": "",
          "url": "https://kabutan.jp/news/marketnews/?b=n202601060096",
          "source": "かぶたん"
        },
        {
          "title": "本日の【均衡表｜3役好転／逆転】引け 好転＝ 173 銘柄 逆転＝ 42 銘柄 (1月5日)(株探ニュース)",
          "snippet": "",
          "url": "https://finance.yahoo.co.jp/news/detail/f8a8f7c3b78432cbfa478fab1074d69d287ee9b3",
          "source": "Yahoo!ファイナンス"
        },
        {
          "title": "前日に動いた銘柄 part1レーザーテック、東京エレクトロン、フジクラなど 執筆： Fisco",
          "snippet": "",
          "url": "https://jp.investing.com/news/stock-market-news/article-1373479",
          "source": "Investing.com - FX | 株式市場 | ファイナンス | 金融ニュース"
        }
      ],
      "link": "https://imtaqin.id/"
    },
    {
      "title": "カービィ",
      "trafficCount": "200+",
      "pubDate": "Wed, 7 Jan 2026 17:10:00 -0800",
      "picture": "https://encrypted-tbn1.gstatic.com/images?q=tbn:ANd9GcQhQev9EbtM9FocLBOyoJKRtsUP1HSFMi1Z96YKnT17y4772LgxnhcyikuUrgw",
      "pictureSource": "ファミ通",
      "relatedSearch": [
        {
          "title": "『星のカービィ』メガネ姿のカービィやすやすや眠るワドルディがかわいい。おうち時間を彩る新作アミューズメント景品が1月より登場",
          "snippet": "",
          "url": "https://www.famitsu.com/article/202601/62685",
          "source": "ファミ通"
        },
        {
          "title": "眼鏡をかけた姿が可愛い！『星のカービィ』プライズシリーズ「Kirby★Diary」に新アイテム―ぬいぐるみ、ブランケットと癒しのおうち時間を過ごせそう（インサイド）",
          "snippet": "",
          "url": "https://news.yahoo.co.jp/articles/a680afede95b4411cbf193c9559e246b4ef91bd3",
          "source": "Yahoo!ニュース"
        },
        {
          "title": "【2026年1月】エスケイジャパン「星のカービィ」登場プライズ一覧",
          "snippet": "",
          "url": "https://www.ndw.jp/kirby-goods-260105/",
          "source": "Nintendo DREAM WEB"
        }
      ],
      "link": "https://imtaqin.id/"
    },
    {
      "title": "第一三共 株価",
      "trafficCount": "200+",
      "pubDate": "Wed, 7 Jan 2026 17:10:00 -0800",
      "picture": "https://encrypted-tbn0.gstatic.com/images?q=tbn:ANd9GcRdqnZXUyW89cGG8IwiLFHqMdgVWtbNBx6Vzu2xY4hhWNed6Yav5vxJFB5Q3Fg",
      "pictureSource": "日経バイオテクONLINE",
      "relatedSearch": [
        {
          "title": "第一三共の2026年見どころ──「ダトロウェイ」のポテンシャルを見定める年、新しい中期経営計画を公表へ",
          "snippet": "",
          "url": "https://bio.nikkeibp.co.jp/atcl/column/16/011900001/25/12/21/00425/",
          "source": "日経バイオテクONLINE"
        },
        {
          "title": "【注目】 話題株ピックアップ【夕刊】（2）：第一三共、アストロＨＤ、日本郵政",
          "snippet": "",
          "url": "https://kabutan.jp/news/marketnews/?b=n202601050694",
          "source": "かぶたん"
        },
        {
          "title": "第一三共の株価反発 「抗がん剤増産へ3000億円」報道を好感",
          "snippet": "",
          "url": "https://www.nikkei.com/article/DGXZQOFL050SF0V00C26A1000000/",
          "source": "日本経済新聞"
        }
      ],
      "link": "https://imtaqin.id/"
    },
    {
      "title": "スポブル",
      "trafficCount": "500+",
      "pubDate": "Wed, 7 Jan 2026 17:00:00 -0800",
      "picture": "https://encrypted-tbn3.gstatic.com/images?q=tbn:ANd9GcTcCEOD_MK3UzuYP0Ga2uemIo5bA2P3eGfFuD45N-Va-u9IfSMqGQDVrssdD4w",
      "pictureSource": "Yahoo!ニュース",
      "relatedSearch": [
        {
          "title": "【春高バレー男子】ベスト16出そろう 強豪・雄物川はストレート勝ち 日本航空は2年ぶり3回戦へ 初出場の関根学園は敗退",
          "snippet": "",
          "url": "https://news.yahoo.co.jp/articles/28d6768c8804486bbcee3843891ab2360cfaaf51",
          "source": "Yahoo!ニュース"
        },
        {
          "title": "雄物川、相手にブロックの的絞らせず 豊富なアタッカー陣を駆使、攻撃多彩",
          "snippet": "",
          "url": "https://www.sakigake.jp/news/article/20260108AK0002/",
          "source": "秋田魁新報電子版"
        },
        {
          "title": "米沢中央が初の8強王手　エース岡崎芽依が活躍、前回8強チーム下す　春高バレー",
          "snippet": "",
          "url": "https://topics.smt.docomo.ne.jp/article/sankei/sports/sankei-_sports_volleyball_W3QKYX2YXRIX5HM7G6XWINSCJQ",
          "source": "ｄメニューニュース"
        }
      ],
      "link": "https://imtaqin.id/"
    }
  ]
}