{
  "lastUpdate": "2026-01-14 22:52:34",
  "data": [
    {
      "title": "afrikamesterskapet",
      "trafficCount": "100+",
      "pubDate": "Wed, 14 Jan 2026 14:20:00 -0800",
      "picture": "https://encrypted-tbn2.gstatic.com/images?q=tbn:ANd9GcROc4M5yK5iJdHbRnVgOoj6wILe7VEOUNGl7QyLHGuxf8PpXW3P91Xh4u5V4rI",
      "pictureSource": "fvn.no",
      "relatedSearch": [
        {
          "title": "Bråk i afrikamesterskapet granskes",
          "snippet": "",
          "url": "https://www.fvn.no/sport/i/d4l7MO/braak-i-afrikamesterskapet-granskes",
          "source": "fvn.no"
        },
        {
          "title": "(+) Bråk i afrikamesterskapet granskes",
          "snippet": "",
          "url": "https://www.folkebladet.no/norgeogverden/i/JOJr7J/braak-i-afrikamesterskapet-granskes",
          "source": "folkebladet.no"
        },
        {
          "title": "Mané knuste Salahs finaledrøm",
          "snippet": "",
          "url": "https://www.tv2.no/sport/mane-knuste-salahs-finaledrom/18463816/",
          "source": "TV2.no"
        }
      ],
      "link": "https://imtaqin.id/"
    },
    {
      "title": "real madrid",
      "trafficCount": "1000+",
      "pubDate": "Wed, 14 Jan 2026 13:10:00 -0800",
      "picture": "https://encrypted-tbn1.gstatic.com/images?q=tbn:ANd9GcQgr7GAbuY0kwfMQbTXyQAXwS17HPBKL3H-YPK01QUnKFAiZIHY8QbAXkYpgls",
      "pictureSource": "Diario AS",
      "relatedSearch": [
        {
          "title": "Albacete - Real Madrid hoy, en directo: octavos de final de Copa del Rey, en vivo en el Belmonte",
          "snippet": "",
          "url": "https://as.com/futbol/copa_del_rey/albacete-real-madrid-hoy-en-directo-octavos-de-final-de-copa-del-rey-en-vivo-en-el-belmonte-f202601-d/",
          "source": "Diario AS"
        },
        {
          "title": "¿Schadenfreude por la eliminación del Real? El post del Barça viene al pelo",
          "snippet": "",
          "url": "https://onefootball.com/de/news/schadenfreude-por-la-eliminacion-del-real-el-post-del-barca-viene-al-pelo-42229749",
          "source": "OneFootball"
        },
        {
          "title": "Así fue el primer gol de Franco Mastantuono en 2026 con el Real Madrid",
          "snippet": "",
          "url": "https://www.365scores.com/es/news/primer-gol-de-franco-mastantuono-en-2026/",
          "source": "365Scores"
        }
      ],
      "link": "https://imtaqin.id/"
    },
    {
      "title": "eivind helland",
      "trafficCount": "200+",
      "pubDate": "Wed, 14 Jan 2026 13:10:00 -0800",
      "picture": "https://encrypted-tbn2.gstatic.com/images?q=tbn:ANd9GcQyJG8FkRXYL2lzJbWHL3mA2q9RGzkXRJ_e3Lr6GZAoGBBeZmnlceUKKwu5Dac",
      "pictureSource": "VG",
      "relatedSearch": [
        {
          "title": "siste: BT: Selges fra Brann for gigantsum",
          "snippet": "",
          "url": "https://www.vg.no/sport/i/6qzV0o/bt-selges-fra-brann-for-gigantsum",
          "source": "VG"
        },
        {
          "title": "Selges for 100 millioner!",
          "snippet": "",
          "url": "https://www.bt.no/sport/ballspark/i/PdRaa7/eivind-helland-selges-fra-brann-til-bologna",
          "source": "Bergens Tidende"
        },
        {
          "title": "Hevder Eivind Helland selges for gigantsum",
          "snippet": "",
          "url": "https://www.nettavisen.no/sport/hevder-eivind-helland-selges-for-gigantsum/s/5-95-2825798",
          "source": "Nettavisen"
        }
      ],
      "link": "https://imtaqin.id/"
    },
    {
      "title": "marokko vs nigeria",
      "trafficCount": "200+",
      "pubDate": "Wed, 14 Jan 2026 13:10:00 -0800",
      "picture": "https://encrypted-tbn0.gstatic.com/images?q=tbn:ANd9GcT5GHwadjbRfKCYqiuq2vwK3jpKeY-7yUyTWJPoudrJ2cFIS8o_ve8acFLFBH0",
      "pictureSource": "NU",
      "relatedSearch": [
        {
          "title": "Live Afrika Cup | Bekijk de tussenstand bij de halve finale Nigeria-Marokko",
          "snippet": "",
          "url": "https://www.nu.nl/voetbal/6382606/live-afrika-cup-bekijk-de-tussenstand-bij-de-halve-finale-nigeria-marokko.html",
          "source": "NU"
        },
        {
          "title": "Marokkaanse droom nog springlevend: finale Afrika Cup een feit na penalty's",
          "snippet": "",
          "url": "https://www.vi.nl/nieuws/marokkaanse-droom-nog-springlevend-finale-afrika-cup-een-feit-na-penalty-s",
          "source": "vi.nl"
        },
        {
          "title": "LIVE Afrika Cup | Saibari test keeper van Nigeria, ex-Ajacied mist mogelijke finale",
          "snippet": "",
          "url": "https://www.gelderlander.nl/voetbal/live-afrika-cup-saibari-test-keeper-van-nigeria-ex-ajacied-mist-mogelijke-finale~a21fb421/",
          "source": "De Gelderlander"
        }
      ],
      "link": "https://imtaqin.id/"
    },
    {
      "title": "ryan hurst",
      "trafficCount": "200+",
      "pubDate": "Wed, 14 Jan 2026 13:00:00 -0800",
      "picture": "https://encrypted-tbn1.gstatic.com/images?q=tbn:ANd9GcQqcugUSK40vx8aaEYFD9cdsXHK1lI1bYQFTrTrvUeFoK02qlHTVoqWNgiu1T8",
      "pictureSource": "Deadline",
      "relatedSearch": [
        {
          "title": "Ryan Hurst Cast As Kratos In Prime Video’s ‘God of War’",
          "snippet": "",
          "url": "https://deadline.com/2026/01/ryan-hurst-cast-kratos-prime-video-god-of-war-1236683097/",
          "source": "Deadline"
        },
        {
          "title": "Amazon didn’t have to go far to find its live-action Kratos",
          "snippet": "",
          "url": "https://www.theverge.com/games/862089/god-of-war-kratos-casting-amazone-prime-video",
          "source": "The Verge"
        },
        {
          "title": "God of War Show Finds Its Kratos in Ragnarok Alum Ryan Hurst",
          "snippet": "",
          "url": "https://www.ign.com/articles/god-of-war-show-finds-its-kratos-in-ragnarok-alum-ryan-hurst",
          "source": "IGN"
        }
      ],
      "link": "https://imtaqin.id/"
    },
    {
      "title": "carabao cup",
      "trafficCount": "200+",
      "pubDate": "Wed, 14 Jan 2026 12:20:00 -0800",
      "picture": "https://encrypted-tbn1.gstatic.com/images?q=tbn:ANd9GcSGyenBfS84ZkyozXq_tfHXxjCEdpSQi2J72tDVnYR8nwwgeOdEEO5sLPedXbw",
      "pictureSource": "BBC",
      "relatedSearch": [
        {
          "title": "Carabao Cup semi-final LIVE: Chelsea vs Arsenal - radio commentary, text updates, stats & head-to-head",
          "snippet": "",
          "url": "https://www.bbc.com/sport/football/live/cp82v1qp9e1t",
          "source": "BBC"
        },
        {
          "title": "Team news: Saliba starts Carabao Cup semi-final | Pre-Match Report | News",
          "snippet": "",
          "url": "https://www.arsenal.com/news/team-news-saliba-starts-carabao-cup-semi-final",
          "source": "Arsenal.com"
        },
        {
          "title": "Confirmed Chelsea line up vs Arsenal | News | Official Site",
          "snippet": "",
          "url": "https://www.chelseafc.com/en/news/article/confirmed-chelsea-line-up-vs-arsenal-carabao-cup",
          "source": "Chelsea"
        }
      ],
      "link": "https://imtaqin.id/"
    },
    {
      "title": "nigeria vs morocco",
      "trafficCount": "1000+",
      "pubDate": "Wed, 14 Jan 2026 11:50:00 -0800",
      "picture": "https://encrypted-tbn1.gstatic.com/images?q=tbn:ANd9GcQF7zUv6NN7dvV7IesPVM-IJFvzt6xuz8aZp5i3X_UvRrBbmc8D5mkk8BR3y3s",
      "pictureSource": "BBC",
      "relatedSearch": [
        {
          "title": "Afcon 2025 semi-finals LIVE: Senegal beat Egypt and hosts Morocco beat Nigeria on penalties",
          "snippet": "",
          "url": "https://www.bbc.com/sport/football/live/c041zwlepl3t",
          "source": "BBC"
        },
        {
          "title": "Nigeria v Morocco: Africa Cup of Nations semi-final goes to extra time – live",
          "snippet": "",
          "url": "https://www.theguardian.com/football/live/2026/jan/14/nigeria-v-morocco-africa-cup-of-nations-semi-final-live",
          "source": "The Guardian"
        },
        {
          "title": "LIVE: Nigeria vs Morocco – AFCON semifinal penalties",
          "snippet": "",
          "url": "https://www.aljazeera.com/sports/liveblog/2026/1/14/live-nigeria-vs-morocco-afcon-2025-semifinal",
          "source": "Al Jazeera"
        }
      ],
      "link": "https://imtaqin.id/"
    },
    {
      "title": "chelsea vs arsenal",
      "trafficCount": "2000+",
      "pubDate": "Wed, 14 Jan 2026 11:30:00 -0800",
      "picture": "https://encrypted-tbn3.gstatic.com/images?q=tbn:ANd9GcSereBMMCQPlDml3wNoMYY4I0831eJOKbolFGvDKy4hhZcQoq8eKIK16aUzPNQ",
      "pictureSource": "BBC",
      "relatedSearch": [
        {
          "title": "Chelsea 2-3 Arsenal LIVE: Carabao Cup semi-final score, commentary, text updates & stats",
          "snippet": "",
          "url": "https://www.bbc.com/sport/football/live/cp82v1qp9e1t",
          "source": "BBC"
        },
        {
          "title": "Chelsea 2-3 Arsenal – player ratings",
          "snippet": "",
          "url": "https://arseblog.news/2026/01/chelsea-2-3-arsenal-player-ratings/",
          "source": "Arseblog News"
        },
        {
          "title": "Chelsea player ratings vs Arsenal: Robert Sanchez shockers prove costly but super-sub Alejandro Garnacho's heroics keep Blues alive in Carabao Cup semi-final",
          "snippet": "",
          "url": "https://www.goal.com/en/lists/chelsea-player-ratings-arsenal-robert-sanchez-alejandro-garnacho-carabao-cup-semi-final/blt9d989e136d491598",
          "source": "Goal.com"
        }
      ],
      "link": "https://imtaqin.id/"
    },
    {
      "title": "vivian motzfeldt",
      "trafficCount": "200+",
      "pubDate": "Wed, 14 Jan 2026 11:30:00 -0800",
      "picture": "https://encrypted-tbn2.gstatic.com/images?q=tbn:ANd9GcTJzGpKee3UVH0LwrUu2hJpYDoXs_5B-PkYY9xq162A8qfG1zg-3Ps0Lwr2emo",
      "pictureSource": "The Guardian",
      "relatedSearch": [
        {
          "title": "Trump intent on conquering Greenland, Danish minister says as talks with US end",
          "snippet": "",
          "url": "https://www.theguardian.com/world/2026/jan/14/greenland-us-trump-talks-denmark",
          "source": "The Guardian"
        },
        {
          "title": "Vance-hosted Greenland meeting ends with ‘fundamental disagreement’",
          "snippet": "",
          "url": "https://www.washingtonpost.com/national-security/2026/01/14/trump-greenland-jd-vance/",
          "source": "The Washington Post"
        },
        {
          "title": "Trump Live Updates: Denmark and U.S. at Odds Over Greenland, Diplomat Says",
          "snippet": "",
          "url": "https://www.nytimes.com/live/2026/01/14/us/trump-news",
          "source": "The New York Times"
        }
      ],
      "link": "https://imtaqin.id/"
    },
    {
      "title": "chelsea mot arsenal",
      "trafficCount": "5000+",
      "pubDate": "Wed, 14 Jan 2026 11:10:00 -0800",
      "picture": "https://encrypted-tbn2.gstatic.com/images?q=tbn:ANd9GcQRMpDvEFgxZEru3YflQ7yQSUsIK40_6ooqi249PChe8aq1FuQa68KSW9I3zl8",
      "pictureSource": "VG",
      "relatedSearch": [
        {
          "title": "Arsenal slo Chelsea – har en fot i ligacup­finalen",
          "snippet": "",
          "url": "https://www.vg.no/sport/i/L4naBx/arsenal-slo-chelsea-har-en-fot-i-ligacupfinalen",
          "source": "VG"
        },
        {
          "title": "- Verdens beste",
          "snippet": "",
          "url": "https://www.dagbladet.no/sport/verdens-beste/84100118",
          "source": "Dagbladet"
        },
        {
          "title": "Arsenal tok første stikk i semifinalen",
          "snippet": "",
          "url": "https://www.tv2.no/sport/arsenal-tok-forste-stikk-i-semifinalen/18464354/",
          "source": "TV2.no"
        }
      ],
      "link": "https://imtaqin.id/"
    }
  ]
}