{
  "lastUpdate": "2025-10-22 11:00:03",
  "data": [
    {
      "title": "weather",
      "trafficCount": "5000+",
      "pubDate": "Tue, 21 Oct 2025 21:20:00 -0700",
      "picture": "https://encrypted-tbn3.gstatic.com/images?q=tbn:ANd9GcRWlnusSXCrGBQ-21I8fkCrZjUGMa_mFDgzvjoyQUyMblclR6wsXVbzxEzJ9uE",
      "pictureSource": "Sacramento Bee",
      "relatedSearch": [
        {
          "title": "Marble-sized hail expected with thunderstorms Wednesday",
          "snippet": "",
          "url": "https://www.sacbee.com/news/weather-news/article312598369.html",
          "source": "Sacramento Bee"
        },
        {
          "title": "Special Weather Statement issued October 22 at 3:02AM PDT by NWS San Francisco CA",
          "snippet": "",
          "url": "https://kioncentralcoast.com/weather-authority/alerts-weather-authority/2025/10/22/special-weather-statement-issued-october-22-at-302am-pdt-by-nws-san-francisco-ca/",
          "source": "KION Central Coast"
        },
        {
          "title": "Special Weather Statement issued October 22 at 2:55AM PDT by NWS San Francisco CA",
          "snippet": "",
          "url": "https://kioncentralcoast.com/weather-authority/alerts-weather-authority/2025/10/22/special-weather-statement-issued-october-22-at-255am-pdt-by-nws-san-francisco-ca/",
          "source": "KION Central Coast"
        }
      ],
      "link": "https://imtaqin.id/"
    },
    {
      "title": "lakers vs warriors",
      "trafficCount": "500+",
      "pubDate": "Tue, 21 Oct 2025 20:50:00 -0700",
      "picture": "https://encrypted-tbn0.gstatic.com/images?q=tbn:ANd9GcSWPdIu__gM-J_TwSjnhk2XZWo5LSz2ax7bjINZclDTc0yRhh0FpS6yBt5NrmU",
      "pictureSource": "basketballsphere.com",
      "relatedSearch": [
        {
          "title": "Injury scare for Luka Doncic, but likely nothing serious",
          "snippet": "",
          "url": "https://basketballsphere.com/en/injury-scare-for-luka-doncic-but-likely-nothing-serious/",
          "source": "basketballsphere.com"
        },
        {
          "title": "Warriors get a 'total team effort' in win over LAL",
          "snippet": "",
          "url": "https://www.nbcsports.com/watch/nba/golden-state-warriors-execute-a-total-team-effort-in-win-over-lakers",
          "source": "NBC Sports"
        },
        {
          "title": "Where Does Luka Doncic's Scoring Night Rank in NBA History?",
          "snippet": "",
          "url": "https://www.si.com/fannation/nba/fastbreak/news/where-does-luka-doncic-s-scoring-night-rank-in-nba-history-01k855a8cexj",
          "source": "Sports Illustrated"
        }
      ],
      "link": "https://imtaqin.id/"
    },
    {
      "title": "nba",
      "trafficCount": "200+",
      "pubDate": "Tue, 21 Oct 2025 19:00:00 -0700",
      "picture": "https://encrypted-tbn3.gstatic.com/images?q=tbn:ANd9GcRHNrFBpUfq63D06t5_TP3ph22iGIeKtT6tWodvPiEISGI3Tm7GmefA3CTXuw0",
      "pictureSource": "The Guardian",
      "relatedSearch": [
        {
          "title": "Thunder win in double OT after raising banner while Warriors handle Lakers",
          "snippet": "",
          "url": "https://www.theguardian.com/sport/2025/oct/21/thunder-see-off-durants-rockets-in-double-ot-after-raising-nba-title-banner",
          "source": "The Guardian"
        },
        {
          "title": "SGA rises for OKC on banner night against Rockets",
          "snippet": "",
          "url": "https://www.nbcsports.com/watch/nba/shai-gilgeous-alexander-rises-for-okc-when-it-matters-most-in-double-ot-win",
          "source": "NBC Sports"
        },
        {
          "title": "Start of the second half",
          "snippet": "",
          "url": "https://www.nytimes.com/athletic/live-blogs/rockets-vs-thunder-live-updates-nba-opening-night-score-result/8adF3hMOREhM/G48hlloHPpNa/",
          "source": "The New York Times"
        }
      ],
      "link": "https://imtaqin.id/"
    },
    {
      "title": "ucl results",
      "trafficCount": "500+",
      "pubDate": "Tue, 21 Oct 2025 14:20:00 -0700",
      "picture": "https://encrypted-tbn0.gstatic.com/images?q=tbn:ANd9GcQxxyFs6gAM7ZOGu5vQoP7LIo_8owS9dOUtUHM7_p7EVCuD35FbC_XxoPTFh9A",
      "pictureSource": "FourFourTwo",
      "relatedSearch": [
        {
          "title": "FourFourTwo's Champions League Predictor: Tell us the results of every UCL fixture and get on our leaderboard",
          "snippet": "",
          "url": "https://www.fourfourtwo.com/features/champions-league-predictor-202526-gw3",
          "source": "FourFourTwo"
        },
        {
          "title": "Champions League: An eventful evening as 43 goals scored, five red cards given, six penalties awarded",
          "snippet": "",
          "url": "https://www.bbc.com/sport/football/articles/c1j8p5w0z7eo",
          "source": "BBC"
        },
        {
          "title": "Champions League highlights and round-up: Paris, Inter and Arsenal win in style to stay perfect, Barcelona score six",
          "snippet": "",
          "url": "https://www.uefa.com/uefachampionsleague/news/029e-1f03c8f544b5-3eecbacb5744-1000--champions-league-highlights-and-round-up-paris-inter-and-a/",
          "source": "UEFA.com"
        }
      ],
      "link": "https://imtaqin.id/"
    },
    {
      "title": "napoli",
      "trafficCount": "200+",
      "pubDate": "Tue, 21 Oct 2025 13:10:00 -0700",
      "picture": "https://encrypted-tbn0.gstatic.com/images?q=tbn:ANd9GcQMBWyU3Fj3jQF3tOzgxz4gRjz9xm8QgwlxGM4GsowrLovuh4jK83yat891bJ4",
      "pictureSource": "Tuttosport",
      "relatedSearch": [
        {
          "title": "\"Una serata di me**a\": Ghoulam-Di Lorenzo, a nudo le fragilità Napoli. Conte-Lang, botta e risposta",
          "snippet": "",
          "url": "https://www.tuttosport.com/news/calcio/serie-a/napoli/2025/10/22-143968830/una_serata_di_me_a_ghoulam-di_lorenzo_a_nudo_le_fragilit_napoli_conte-lang_botta_e_risposta",
          "source": "Tuttosport"
        },
        {
          "title": "#Létang si è sfogato dopo la partita col #Lione. È accusato di aver offeso la direzione di gara. Resta il nodo politico, non si riferiva solo alla partita della sua squadra",
          "snippet": "",
          "url": "https://www.facebook.com/story.php?story_fbid=1332378558900796&id=100063859936263",
          "source": "Facebook"
        },
        {
          "title": "Conte, cosa c’è dietro lo sfogo di Eindhoven: i “troppi” acquisti e la solita crisi del secondo anno",
          "snippet": "",
          "url": "https://www.repubblica.it/sport/calcio/serie-a/napoli/2025/10/22/news/conte_napoli_psv_eindhoven-424929637/",
          "source": "la Repubblica"
        }
      ],
      "link": "https://imtaqin.id/"
    },
    {
      "title": "hull city vs leicester city",
      "trafficCount": "200+",
      "pubDate": "Tue, 21 Oct 2025 12:40:00 -0700",
      "picture": "https://encrypted-tbn1.gstatic.com/images?q=tbn:ANd9GcRR1nVxL7Su60wNIBxntQtSOq6NKJKKoe6SmXJ7mqbLCsQF-W66cvc0UhmUoaA",
      "pictureSource": "Africa Top Sports",
      "relatedSearch": [
        {
          "title": "Jordan Ayew Registers First Assist of the Season Despite Leicester Defeat",
          "snippet": "",
          "url": "https://en.africatopsports.com/2025/10/22/jordan-ayew-registers-first-assist-of-the-season-despite-leicester-defeat/",
          "source": "Africa Top Sports"
        },
        {
          "title": "Holden praises 'grit, desire and quality'",
          "snippet": "",
          "url": "https://ca.sports.yahoo.com/news/holden-praises-grit-desire-quality-220407952.html",
          "source": "Yahoo"
        },
        {
          "title": "Liam Millar back with a bang as Hull stretch winning run against Leicester",
          "snippet": "",
          "url": "https://www.sidmouthherald.co.uk/sport/national/25561553.liam-millar-back-bang-hull-stretch-winning-run-leicester/",
          "source": "Sidmouth Herald"
        }
      ],
      "link": "https://imtaqin.id/"
    },
    {
      "title": "man city",
      "trafficCount": "2000+",
      "pubDate": "Tue, 21 Oct 2025 12:30:00 -0700",
      "picture": "https://encrypted-tbn0.gstatic.com/images?q=tbn:ANd9GcTfr3TRZQEZ1qeoA4Hsz4PtKWH3Iv4IcUfXXctb3OuzXKIDsYW61RrJe078sdg",
      "pictureSource": "Manchester Evening News",
      "relatedSearch": [
        {
          "title": "Manchester City fan, 35, found dead in Spain hours before Villarreal match as devastated family pay tribute",
          "snippet": "",
          "url": "https://www.manchestereveningnews.co.uk/news/greater-manchester-news/manchester-city-fan-35-found-32723740",
          "source": "Manchester Evening News"
        },
        {
          "title": "Man City helping to return body of fan who died before Villarreal game",
          "snippet": "",
          "url": "https://www.thetimes.com/sport/football/article/manchester-city-fan-death-news-guy-bradshaw-73zc033nk",
          "source": "The Times"
        },
        {
          "title": "Man City fan and 'devoted dad' dies after travelling to Benidorm to watch them in Champions League",
          "snippet": "",
          "url": "https://www.dailymail.co.uk/sport/football/article-15215745/Man-City-fan-dies-travelling-Benidorm-watch-Champions-League.html",
          "source": "Daily Mail"
        }
      ],
      "link": "https://imtaqin.id/"
    },
    {
      "title": "al-hilal vs al sadd",
      "trafficCount": "100+",
      "pubDate": "Tue, 21 Oct 2025 12:30:00 -0700",
      "picture": "https://encrypted-tbn2.gstatic.com/images?q=tbn:ANd9GcTZNRsnujR9foBBRYbUGJhTTh15cfFhusrmCaEPNwyIvGGgtJKut6xuesP-t4U",
      "pictureSource": "Reuters",
      "relatedSearch": [
        {
          "title": "Koulibaly on target as Al-Hilal remain perfect in Asian Champions League",
          "snippet": "",
          "url": "https://www.reuters.com/sports/soccer/koulibaly-target-al-hilal-remain-perfect-asian-champions-league-2025-10-21/",
          "source": "Reuters"
        },
        {
          "title": "Al Sadd eye points in key match against Al Hilal| Gulf Times",
          "snippet": "",
          "url": "https://www.gulf-times.com/article/713258/sports/al-sadd-eye-points-in-key-match-against-al-hilal",
          "source": "Gulf Times"
        },
        {
          "title": "Al-Hilal beat Al-Sadd to stay top of AFC Champions League Elite Group B",
          "snippet": "",
          "url": "https://www.arabnews.com/node/2619743/sport",
          "source": "Arab News"
        }
      ],
      "link": "https://imtaqin.id/"
    },
    {
      "title": "copenhagen vs dortmund",
      "trafficCount": "1000+",
      "pubDate": "Tue, 21 Oct 2025 12:20:00 -0700",
      "picture": "https://encrypted-tbn0.gstatic.com/images?q=tbn:ANd9GcQOrzy16y6XfqPFLqJK9X5bppyfgqu--3PbzQDdxJfBk6e5-Pl-oh_SmuqGVso",
      "pictureSource": "SZ.de",
      "relatedSearch": [
        {
          "title": "Dortmund schlägt Kopenhagen: Die deutlichen Fingerzeige von Felix Nmecha",
          "snippet": "",
          "url": "https://www.sueddeutsche.de/sport/dortmund-nmecha-kopenhagen-champions-league-li.3328928",
          "source": "SZ.de"
        },
        {
          "title": "BVB-Verteidiger erhält Monster-Lob: „Der technisch stärkste Spieler“",
          "snippet": "",
          "url": "https://www.ruhr24.de/bvb/bvb-verteidiger-ramy-bensebaini-lob-elfmeter-tor-niko-kovac-fc-kopenhagen-borussia-dortmund-93999289.html",
          "source": "Ruhr24"
        },
        {
          "title": "Kovac: \"Wichtiger Sieg nach der Niederlage in München\"",
          "snippet": "",
          "url": "https://www.sport.de/video/en605935/kovac-wichtiger-sieg-nach-der-niederlage-in-muenchen/",
          "source": "Sport.de"
        }
      ],
      "link": "https://imtaqin.id/"
    },
    {
      "title": "psg",
      "trafficCount": "1000+",
      "pubDate": "Tue, 21 Oct 2025 12:20:00 -0700",
      "picture": "https://encrypted-tbn2.gstatic.com/images?q=tbn:ANd9GcTPpKNNzQ3Cz3oDzI0HBqugUefITpmEjhqPipKVIF1fC_L-enCEes9Jp7NGoNQ",
      "pictureSource": "Foot Mercato",
      "relatedSearch": [
        {
          "title": "Bayer : Tapsoba lucide après l’expulsion d’Andrich et la défaite face au PSG",
          "snippet": "",
          "url": "https://www.footmercato.net/a6262568486686703610-bayer-tapsoba-lucide-apres-lexpulsion-dandrich-et-la-defaite-face-au-psg",
          "source": "Foot Mercato"
        },
        {
          "title": "C1 : Paris prend l'avantage, Haaland déjà décisif !",
          "snippet": "",
          "url": "https://onefootball.com/es/noticias/c1-paris-prend-lavantage-haaland-deja-decisif-41836688",
          "source": "OneFootball"
        },
        {
          "title": "Foot : Le PSG égale un record historique en Ligue des champions, une année 2025 exceptionnelle",
          "snippet": "",
          "url": "https://www.aa.com.tr/fr/sport/foot-le-psg-%C3%A9gale-un-record-historique-en-ligue-des-champions-une-ann%C3%A9e-2025-exceptionnelle/3723440",
          "source": "Anadolu Ajansı"
        }
      ],
      "link": "https://imtaqin.id/"
    }
  ]
}